{"name":"Computational Geometry","slug":"Computational-Geometry","count":1,"postlist":[{"title":"è®­ç»ƒç¬”è®° - è®¡ç®—å‡ ä½•","uid":"d3efaf25e370a6934d01ee2c4302e610","slug":"ComputationalGeometry","date":"2021-04-13T04:23:08.000Z","updated":"2022-04-03T06:15:49.090Z","comments":true,"path":"api/articles/ComputationalGeometry.json","keywords":null,"cover":"https://img0.baidu.com/it/u=1184252829,2831577942&fm=253&fmt=auto&app=138&f=JPEG?w=500&h=367","text":"è®¡ç®—å‡ ä½•åŸºç¡€å…¥é—¨è®¡ç®—å‡ ä½•æ˜¯ç”±å¾®åˆ†å‡ ä½•ã€ä»£æ•°å‡ ä½•ã€æ•°å€¼è®¡ç®—ã€é€¼è¿‘è®ºã€æ‹“æ‰‘å­¦ä»¥åŠæ•°æ§æŠ€æœ¯ç­‰å½¢æˆçš„ä¸€é—¨æ–°å…´è¾¹ç¼˜å­¦ç§‘ï¼Œå…¶ä¸»è¦ç ”ç©¶å¯¹è±¡å’Œå†…å®¹æ˜¯å¯¹è‡ªç”±å½¢æ›²çº¿ã€æ›²é¢çš„æ•°å­¦æè¿°ã€è®¾è®¡ã€åˆ†æåŠå›¾å½¢çš„æ˜¾ç¤ºã€å¤„ç†ç­‰ã€‚ å¯¹äºæµ®ç‚¹æ•°çš„å¤„ç†ä¸è¦ç›´æ¥ç”¨ç­‰å·åˆ¤æ–­æµ®ç‚¹æ•°æ˜¯å¦ç›¸ç­‰ï¼ åŒæ ·çš„ä¸€ä¸ªæ•°1.5ã€‚å¦‚æœä»ä¸åŒçš„...","link":"","photos":[],"count_time":{"symbolsCount":"2k","symbolsTime":"2 mins."},"categories":[{"name":"notes","slug":"notes","count":3,"path":"api/categories/notes.json"}],"tags":[{"name":"Algorithm","slug":"Algorithm","count":5,"path":"api/tags/Algorithm.json"},{"name":"ACM","slug":"ACM","count":4,"path":"api/tags/ACM.json"},{"name":"Computational Geometry","slug":"Computational-Geometry","count":1,"path":"api/tags/Computational-Geometry.json"}],"author":{"name":"ğš‚ğšğš—ğš’ğšœğšğ™²","slug":"blog-author","avatar":"/assets/img/favicon.png","link":"/","description":"ğš‚ğšğš—ğš’ğšœğšğ™² is a pigeon from SouthWest University","socials":{"github":"","twitter":"","stackoverflow":"","wechat":"","qq":"","weibo":"","zhihu":"","csdn":"","juejin":"","customs":{"bilibili":{"icon":"/assets/svg/bilibili.svg","link":"https://space.bilibili.com/25394898"},"live":{"icon":"/assets/svg/live.svg","link":"https://live.bilibili.com/5184681"},"github":{"icon":"/assets/svg/github.svg","link":"https://github.com/sunist-c"},"institution":{"icon":"/assets/svg/institution.svg","link":"https://github.com/swu-acm-lab"},"outlook":{"icon":"/assets/svg/outlook.svg","link":"mailto:sunist@mail.swu-acm.cn"}}}}}]}